sc_client/__init__.py
sc_client/_internal_utils.py
sc_client/sc_keynodes.py
sc_client/session.py
sc_client/client/__init__.py
sc_client/client/_api.py
sc_client/client/_executor.py
sc_client/client/_payload_factory.py
sc_client/client/_response_processor.py
sc_client/constants/__init__.py
sc_client/constants/common.py
sc_client/constants/exceptions.py
sc_client/constants/numeric.py
sc_client/constants/sc_type/__init__.py
sc_client/constants/sc_type/bitmasks.py
sc_client/constants/sc_type/sc_type.py
sc_client/constants/sc_types/__init__.py
sc_client/models/__init__.py
sc_client/models/sc_addr.py
sc_client/models/sc_construction.py
sc_client/models/sc_event_subscription.py
sc_client/models/sc_template.py
sc_client/models/scs.py
py_sc_client-0.4.0.dist-info/LICENSE
py_sc_client-0.4.0.dist-info/METADATA
py_sc_client-0.4.0.dist-info/WHEEL
py_sc_client-0.4.0.dist-info/top_level.txt
py_sc_client-0.4.0.dist-info/RECORD
