Metadata-Version: 2.1
Name: py-sc-client
Version: 0.4.0
Summary: The Python implementation of the client for communication with the sc-server
Home-page: https://github.com/ostis-ai/py-sc-client
Author: ostis-ai
License: MIT
Project-URL: Bug Reports, https://github.com/ostis-ai/py-sc-client/issues
Project-URL: Source, https://github.com/ostis-ai/py-sc-client
Keywords: sc-client,sc client
Classifier: Topic :: Software Development :: Libraries :: Python Modules
Classifier: Intended Audience :: Developers
Classifier: License :: OSI Approved :: MIT License
Classifier: Programming Language :: Python :: 3
Classifier: Programming Language :: Python :: 3.8
Classifier: Programming Language :: Python :: 3.9
Classifier: Programming Language :: Python :: 3.10
Classifier: Programming Language :: Python :: 3.11
Classifier: Programming Language :: Python :: 3.12
Requires-Python: >=3.8, <4
License-File: LICENSE
Requires-Dist: websocket-client>=1.0.1
